robokop_genetics/__init__.py
robokop_genetics/genetics_cache.py
robokop_genetics/genetics_normalization.py
robokop_genetics/genetics_services.py
robokop_genetics/node_types.py
robokop_genetics/simple_graph_components.py
robokop_genetics/util.py
robokop_genetics/services/__init__.py
robokop_genetics/services/clingen.py
robokop_genetics/services/ensembl.py
robokop_genetics/services/hgnc.py
robokop_genetics-0.7.0.dist-info/licenses/LICENSE
robokop_genetics-0.7.0.dist-info/METADATA
robokop_genetics-0.7.0.dist-info/WHEEL
robokop_genetics-0.7.0.dist-info/top_level.txt
robokop_genetics-0.7.0.dist-info/RECORD
