Metadata-Version: 2.4
Name: robokop-genetics
Version: 0.7.0
Summary: A package for Robokop genetics tools and services.
Home-page: https://github.com/RobokopU24/robokop-genetics
Author: Evan Morris
Author-email: evandietzmorris@gmail.com
Maintainer: Evan Morris
Maintainer-email: evandietzmorris@gmail.com
License: CC-0
Classifier: Programming Language :: Python :: 3
Classifier: License :: OSI Approved :: MIT License
Classifier: Operating System :: OS Independent
Requires-Python: >=3.9
License-File: LICENSE
Requires-Dist: bmt>=1.4.6
Requires-Dist: requests>=2.32.3
Requires-Dist: redis>=5.0.4
Dynamic: author
Dynamic: author-email
Dynamic: classifier
Dynamic: description
Dynamic: description-content-type
Dynamic: home-page
Dynamic: license
Dynamic: license-file
Dynamic: maintainer
Dynamic: maintainer-email
Dynamic: requires-dist
Dynamic: requires-python
Dynamic: summary
